{
    "destination": [
        {
            "id": "1",
            "value": 70,
            "label": "Atlanta (no hotels err)"
        },
        {
            "id": "2",
            "value": 149,
            "label": "Boston"
        },
        {
            "id": "4",
            "value": 34501,
            "label": "Celebration"
        },
        {
            "id": "5",
            "value": 40418,
            "label": "Edgewood"
        },
        {
            "id": "6",
            "value": 39505,
            "label": "Gotha"
        },
        {
            "id": "7",
            "value": 21017,
            "label": "Haines City"
        },
        {
            "id": "8",
            "value": 10,
            "label": "Los Angeles"
        },
        {
            "id": "9",
            "value": 72,
            "label": "Miami"
        },
        {
            "id": "10",
            "value": 18421,
            "label": "Montverde"
        },
        {
            "id": "11",
            "value": 54,
            "label": "New York"
        },
        {
            "id": "12",
            "value": 23767,
            "label": "Ocoee"
        },
        {
            "id": "13",
            "value": 32190,
            "label": "Orlando area"
        },
        {
            "id": "14",
            "value": 11531,
            "label": "Poinciana"
        },
        {
            "id": "15",
            "value": 10772,
            "label": "Polk City"
        },
        {
            "id": "16",
            "value": 17969,
            "label": "San Francisco Bay"
        },
        {
            "id": "17",
            "value": 17365,
            "label": "St. Cloud"
        },
        {
            "id": "18",
            "value": 24263,
            "label": "Walt Disney World\u00ae Resort"
        },
        {
            "id": "19",
            "value": 277,
            "label": "Washington"
        },
        {
            "id": "20",
            "value": 49764,
            "label": "Windermere"
        },
        {
            "id": "21",
            "value": 22282,
            "label": "Winter Garden"
        }
    ],
    "hotels": [
        {
            "id": "cf6b5a25-da43-4e84-815b-b6e6b84c1df0",
            "name": "Atlanta Hotel 1",
            "address": "7301 Atlanta St",
            "city": "Atlanta",
            "state": "FL",
            "country_code": "US",
            "hotel_rating": 4.9,
            "phone_number": "+1 305 555 3717",
            "website": null
        },
        {
            "id": "5c17c8c0-5a75-42b4-8317-59607f34c4df",
            "name": "Atlanta Hotel 2",
            "address": "4107 Atlanta St",
            "city": "Atlanta",
            "state": "FL",
            "country_code": "US",
            "hotel_rating": 4.2,
            "phone_number": "+1 305 555 5217",
            "website": null
        },
        {
            "id": "9200f2b1-914f-4df1-9ab7-30fd9a7015a9",
            "name": "Atlanta Hotel 3",
            "address": "1906 Atlanta St",
            "city": "Atlanta",
            "state": "FL",
            "country_code": "US",
            "hotel_rating": 4.6,
            "phone_number": "+1 305 555 9952",
            "website": null
        },
        {
            "id": "cb333a50-741e-4666-9c41-b6a6ac0d88fa",
            "name": "Atlanta Hotel 4",
            "address": "9493 Atlanta St",
            "city": "Atlanta",
            "state": "FL",
            "country_code": "US",
            "hotel_rating": 4.1,
            "phone_number": "+1 305 555 1821",
            "website": null
        },
        {
            "id": "0bd32d4f-5c06-41aa-bfa0-f9984110a093",
            "name": "Atlanta Hotel 5",
            "address": "73 Atlanta St",
            "city": "Atlanta",
            "state": "FL",
            "country_code": "US",
            "hotel_rating": 2.6,
            "phone_number": "+1 305 555 4435",
            "website": null
        },
        {
            "id": "c45f2231-aca6-41b1-a85b-ffdc4a30279d",
            "name": "Atlanta Hotel 6",
            "address": "9031 Atlanta St",
            "city": "Atlanta",
            "state": "FL",
            "country_code": "US",
            "hotel_rating": 3.6,
            "phone_number": "+1 305 555 9129",
            "website": null
        },
        {
            "id": "646f5861-c437-46da-a5a5-f34e099a8e60",
            "name": "Boston Hotel 1",
            "address": "8454 Boston St",
            "city": "Boston",
            "state": "FL",
            "country_code": "US",
            "hotel_rating": 2.6,
            "phone_number": "+1 305 555 5136",
            "website": null
        },
        {
            "id": "74eec472-d40e-44f9-97c3-f775098e7606",
            "name": "Boston Hotel 2",
            "address": "7288 Boston St",
            "city": "Boston",
            "state": "FL",
            "country_code": "US",
            "hotel_rating": 4.7,
            "phone_number": "+1 305 555 9928",
            "website": null
        },
        {
            "id": "eb0ce012-b102-423b-a73d-f4b3da9c0c9b",
            "name": "Boston Hotel 3",
            "address": "9373 Boston St",
            "city": "Boston",
            "state": "FL",
            "country_code": "US",
            "hotel_rating": 4.5,
            "phone_number": "+1 305 555 9788",
            "website": "https://www.bostonhotel3.com"
        },
        {
            "id": "773557e5-a364-43e2-83fc-c90bad6780c8",
            "name": "Boston Hotel 4",
            "address": "9793 Boston St",
            "city": "Boston",
            "state": "FL",
            "country_code": "US",
            "hotel_rating": 3.2,
            "phone_number": "+1 305 555 3864",
            "website": null
        },
        {
            "id": "6261283a-95d4-487c-9edb-50eab729d622",
            "name": "Boston Hotel 5",
            "address": "4135 Boston St",
            "city": "Boston",
            "state": "FL",
            "country_code": "US",
            "hotel_rating": 4.4,
            "phone_number": "+1 305 555 6055",
            "website": null
        },
        {
            "id": "b5f4ca70-af31-401d-996d-4150a15211fa",
            "name": "Boston Hotel 6",
            "address": "4987 Boston St",
            "city": "Boston",
            "state": "FL",
            "country_code": "US",
            "hotel_rating": 2.2,
            "phone_number": "+1 305 555 5907",
            "website": null
        },
        {
            "id": "3b239b75-9cfa-4eab-b824-8ba8fdb9ea7d",
            "name": "Boston Hotel 1",
            "address": "5437 Boston St",
            "city": "Boston",
            "state": "FL",
            "country_code": "US",
            "hotel_rating": 2.4,
            "phone_number": "+1 305 555 5109",
            "website": null
        },
        {
            "id": "77413d48-74ce-4420-872c-8c51f84afdad",
            "name": "Boston Hotel 2",
            "address": "6151 Boston St",
            "city": "Boston",
            "state": "FL",
            "country_code": "US",
            "hotel_rating": 2.5,
            "phone_number": "+1 305 555 4589",
            "website": null
        },
        {
            "id": "d3ac323e-e61d-44a3-a626-362abbbb6afa",
            "name": "Boston Hotel 3",
            "address": "1538 Boston St",
            "city": "Boston",
            "state": "FL",
            "country_code": "US",
            "hotel_rating": 4.7,
            "phone_number": "+1 305 555 8388",
            "website": null
        },
        {
            "id": "513e7fa6-f6ea-4434-8452-02f5f6d06cbb",
            "name": "Boston Hotel 4",
            "address": "9091 Boston St",
            "city": "Boston",
            "state": "FL",
            "country_code": "US",
            "hotel_rating": 2.7,
            "phone_number": "+1 305 555 7279",
            "website": null
        },
        {
            "id": "a2341d53-8290-4d09-a1d3-a18ab026deac",
            "name": "Boston Hotel 5",
            "address": "203 Boston St",
            "city": "Boston",
            "state": "FL",
            "country_code": "US",
            "hotel_rating": 5.0,
            "phone_number": "+1 305 555 8681",
            "website": null
        },
        {
            "id": "906d873a-b996-4780-a289-b4de7455d50b",
            "name": "Boston Hotel 6",
            "address": "8774 Boston St",
            "city": "Boston",
            "state": "FL",
            "country_code": "US",
            "hotel_rating": 4.0,
            "phone_number": "+1 305 555 5088",
            "website": null
        },
        {
            "id": "f42a60bc-965c-41f2-b3c9-c710bdee0dc4",
            "name": "Celebration Hotel 1",
            "address": "4522 Celebration St",
            "city": "Celebration",
            "state": "FL",
            "country_code": "US",
            "hotel_rating": 2.6,
            "phone_number": "+1 305 555 1266",
            "website": null
        },
        {
            "id": "3ca72cac-423e-4f8b-8a30-121f2081626f",
            "name": "Celebration Hotel 2",
            "address": "1489 Celebration St",
            "city": "Celebration",
            "state": "FL",
            "country_code": "US",
            "hotel_rating": 2.1,
            "phone_number": "+1 305 555 2243",
            "website": null
        },
        {
            "id": "f36fda00-3439-463c-9673-281de3261249",
            "name": "Celebration Hotel 3",
            "address": "5274 Celebration St",
            "city": "Celebration",
            "state": "FL",
            "country_code": "US",
            "hotel_rating": 4.8,
            "phone_number": "+1 305 555 7975",
            "website": null
        },
        {
            "id": "d7fac43a-e1e1-4b37-a1df-bfcb41a25d49",
            "name": "Celebration Hotel 4",
            "address": "3342 Celebration St",
            "city": "Celebration",
            "state": "FL",
            "country_code": "US",
            "hotel_rating": 2.2,
            "phone_number": "+1 305 555 7420",
            "website": null
        },
        {
            "id": "43804e6f-6477-48c5-a503-1ff32e68ee21",
            "name": "Celebration Hotel 5",
            "address": "5386 Celebration St",
            "city": "Celebration",
            "state": "FL",
            "country_code": "US",
            "hotel_rating": 3.6,
            "phone_number": "+1 305 555 7545",
            "website": null
        },
        {
            "id": "943cff81-febc-49d4-bfce-797342db50a2",
            "name": "Celebration Hotel 6",
            "address": "3603 Celebration St",
            "city": "Celebration",
            "state": "FL",
            "country_code": "US",
            "hotel_rating": 4.9,
            "phone_number": "+1 305 555 6793",
            "website": null
        },
        {
            "id": "74880fa6-1b01-438b-a17b-0cd87b082f8b",
            "name": "Edgewood Hotel 1",
            "address": "5493 Edgewood St",
            "city": "Edgewood",
            "state": "FL",
            "country_code": "US",
            "hotel_rating": 4.0,
            "phone_number": "+1 305 555 8592",
            "website": null
        },
        {
            "id": "efff2bed-3ac1-4583-8778-9bbcd81b4a4a",
            "name": "Edgewood Hotel 2",
            "address": "2159 Edgewood St",
            "city": "Edgewood",
            "state": "FL",
            "country_code": "US",
            "hotel_rating": 4.2,
            "phone_number": "+1 305 555 8344",
            "website": null
        },
        {
            "id": "2af89f81-f22f-42fa-b330-775fbd3430cc",
            "name": "Edgewood Hotel 3",
            "address": "2966 Edgewood St",
            "city": "Edgewood",
            "state": "FL",
            "country_code": "US",
            "hotel_rating": 4.1,
            "phone_number": "+1 305 555 1012",
            "website": null
        },
        {
            "id": "a8344a2b-ace4-4ed5-9ce7-43c49e92687b",
            "name": "Edgewood Hotel 4",
            "address": "529 Edgewood St",
            "city": "Edgewood",
            "state": "FL",
            "country_code": "US",
            "hotel_rating": 4.8,
            "phone_number": "+1 305 555 6199",
            "website": null
        },
        {
            "id": "cc763517-71c0-497c-8e46-37489ff19810",
            "name": "Edgewood Hotel 5",
            "address": "4254 Edgewood St",
            "city": "Edgewood",
            "state": "FL",
            "country_code": "US",
            "hotel_rating": 3.2,
            "phone_number": "+1 305 555 8537",
            "website": null
        },
        {
            "id": "0c90f932-5a59-4019-a069-1431abcb2944",
            "name": "Edgewood Hotel 6",
            "address": "5525 Edgewood St",
            "city": "Edgewood",
            "state": "FL",
            "country_code": "US",
            "hotel_rating": 3.9,
            "phone_number": "+1 305 555 4817",
            "website": null
        },
        {
            "id": "fb601e97-8c64-4aa9-963a-3ebbfbaf8f58",
            "name": "Gotha Hotel 1",
            "address": "1001 Gotha St",
            "city": "Gotha",
            "state": "FL",
            "country_code": "US",
            "hotel_rating": 2.9,
            "phone_number": "+1 305 555 3516",
            "website": null
        },
        {
            "id": "4ec8ed35-f764-4e36-835e-f5d743c70172",
            "name": "Gotha Hotel 2",
            "address": "7635 Gotha St",
            "city": "Gotha",
            "state": "FL",
            "country_code": "US",
            "hotel_rating": 4.6,
            "phone_number": "+1 305 555 2318",
            "website": null
        },
        {
            "id": "ef81a2f8-15a4-4fdf-8694-2106eca01d37",
            "name": "Gotha Hotel 3",
            "address": "5417 Gotha St",
            "city": "Gotha",
            "state": "FL",
            "country_code": "US",
            "hotel_rating": 3.2,
            "phone_number": "+1 305 555 9779",
            "website": null
        },
        {
            "id": "56ca4a74-4a10-4674-ad49-898fb583b71d",
            "name": "Gotha Hotel 4",
            "address": "838 Gotha St",
            "city": "Gotha",
            "state": "FL",
            "country_code": "US",
            "hotel_rating": 4.5,
            "phone_number": "+1 305 555 6178",
            "website": null
        },
        {
            "id": "0293eb15-b0ea-4ad7-a409-6755226878de",
            "name": "Gotha Hotel 5",
            "address": "1583 Gotha St",
            "city": "Gotha",
            "state": "FL",
            "country_code": "US",
            "hotel_rating": 4.9,
            "phone_number": "+1 305 555 9633",
            "website": null
        },
        {
            "id": "76f4126a-2dad-4c0e-acb0-915a01b8a731",
            "name": "Gotha Hotel 6",
            "address": "4393 Gotha St",
            "city": "Gotha",
            "state": "FL",
            "country_code": "US",
            "hotel_rating": 2.3,
            "phone_number": "+1 305 555 3426",
            "website": null
        },
        {
            "id": "07cc043d-0d48-4e44-bb79-dc956c30bc65",
            "name": "Haines City Hotel 1",
            "address": "1796 Haines City St",
            "city": "Haines City",
            "state": "FL",
            "country_code": "US",
            "hotel_rating": 3.1,
            "phone_number": "+1 305 555 1072",
            "website": null
        },
        {
            "id": "7091f317-c946-41ae-aa77-c3f2a4fda381",
            "name": "Haines City Hotel 2",
            "address": "579 Haines City St",
            "city": "Haines City",
            "state": "FL",
            "country_code": "US",
            "hotel_rating": 3.2,
            "phone_number": "+1 305 555 3506",
            "website": null
        },
        {
            "id": "6732c64f-0067-424c-948a-53ad0a93a9e7",
            "name": "Haines City Hotel 3",
            "address": "2970 Haines City St",
            "city": "Haines City",
            "state": "FL",
            "country_code": "US",
            "hotel_rating": 3.4,
            "phone_number": "+1 305 555 9866",
            "website": null
        },
        {
            "id": "dd270f85-72ec-4fd9-9d13-d8f9076bca1e",
            "name": "Haines City Hotel 4",
            "address": "3596 Haines City St",
            "city": "Haines City",
            "state": "FL",
            "country_code": "US",
            "hotel_rating": 3.0,
            "phone_number": "+1 305 555 8332",
            "website": null
        },
        {
            "id": "7d61393e-99cf-41f7-8dba-4f800127e1f2",
            "name": "Haines City Hotel 5",
            "address": "2992 Haines City St",
            "city": "Haines City",
            "state": "FL",
            "country_code": "US",
            "hotel_rating": 2.5,
            "phone_number": "+1 305 555 2278",
            "website": null
        },
        {
            "id": "f2cef0b7-c53c-4741-923b-296dec4ed0cf",
            "name": "Haines City Hotel 6",
            "address": "5633 Haines City St",
            "city": "Haines City",
            "state": "FL",
            "country_code": "US",
            "hotel_rating": 2.7,
            "phone_number": "+1 305 555 2556",
            "website": null
        },
        {
            "id": "a49ebb09-2ac8-4312-b23d-82670130d5db",
            "name": "Los Angeles Hotel 1",
            "address": "1925 Los Angeles St",
            "city": "Los Angeles",
            "state": "FL",
            "country_code": "US",
            "hotel_rating": 4.4,
            "phone_number": "+1 305 555 2555",
            "website": null
        },
        {
            "id": "e1891b92-0962-48d0-8c98-cf7b5a5af4fe",
            "name": "Los Angeles Hotel 2",
            "address": "4528 Los Angeles St",
            "city": "Los Angeles",
            "state": "FL",
            "country_code": "US",
            "hotel_rating": 4.0,
            "phone_number": "+1 305 555 2590",
            "website": null
        },
        {
            "id": "15ae0f10-d6e9-47dc-9d0e-4e9eb4957466",
            "name": "Los Angeles Hotel 3",
            "address": "592 Los Angeles St",
            "city": "Los Angeles",
            "state": "FL",
            "country_code": "US",
            "hotel_rating": 5.0,
            "phone_number": "+1 305 555 4593",
            "website": null
        },
        {
            "id": "a8fff0af-e8c3-4ebf-873f-4155deb76d36",
            "name": "Los Angeles Hotel 4",
            "address": "8211 Los Angeles St",
            "city": "Los Angeles",
            "state": "FL",
            "country_code": "US",
            "hotel_rating": 4.5,
            "phone_number": "+1 305 555 6614",
            "website": null
        },
        {
            "id": "bff59121-bce3-4791-9f07-efd0f47b7101",
            "name": "Los Angeles Hotel 5",
            "address": "1688 Los Angeles St",
            "city": "Los Angeles",
            "state": "FL",
            "country_code": "US",
            "hotel_rating": 4.3,
            "phone_number": "+1 305 555 9181",
            "website": null
        },
        {
            "id": "bdc551f3-95f5-430d-a7ce-febf5af85433",
            "name": "Los Angeles Hotel 6",
            "address": "7682 Los Angeles St",
            "city": "Los Angeles",
            "state": "FL",
            "country_code": "US",
            "hotel_rating": 3.2,
            "phone_number": "+1 305 555 4143",
            "website": null
        },
        {
            "id": "9cc4755e-7e8a-4123-8f64-1f82935eed26",
            "name": "Miami Hotel 1",
            "address": "7483 Miami St",
            "city": "Miami",
            "state": "FL",
            "country_code": "US",
            "hotel_rating": 2.0,
            "phone_number": "+1 305 555 2224",
            "website": null
        },
        {
            "id": "f26ade73-e563-4e0a-a420-f5df41f994c0",
            "name": "Miami Hotel 2",
            "address": "3333 Miami St",
            "city": "Miami",
            "state": "FL",
            "country_code": "US",
            "hotel_rating": 2.2,
            "phone_number": "+1 305 555 3703",
            "website": null
        },
        {
            "id": "e41c8b2b-4775-4bcc-9185-d8126a72c951",
            "name": "Miami Hotel 3",
            "address": "7814 Miami St",
            "city": "Miami",
            "state": "FL",
            "country_code": "US",
            "hotel_rating": 3.2,
            "phone_number": "+1 305 555 9509",
            "website": null
        },
        {
            "id": "9c95a14a-2ac6-4326-aa00-0e5ee408b54c",
            "name": "Miami Hotel 4",
            "address": "6861 Miami St",
            "city": "Miami",
            "state": "FL",
            "country_code": "US",
            "hotel_rating": 4.9,
            "phone_number": "+1 305 555 3483",
            "website": null
        },
        {
            "id": "4415ee78-80ad-4b07-bf6a-cf42551e59a6",
            "name": "Miami Hotel 5",
            "address": "2246 Miami St",
            "city": "Miami",
            "state": "FL",
            "country_code": "US",
            "hotel_rating": 2.9,
            "phone_number": "+1 305 555 5080",
            "website": null
        },
        {
            "id": "ed105e55-7a9f-4b32-9b14-03c9a1185691",
            "name": "Miami Hotel 6",
            "address": "8792 Miami St",
            "city": "Miami",
            "state": "FL",
            "country_code": "US",
            "hotel_rating": 4.3,
            "phone_number": "+1 305 555 6930",
            "website": null
        },
        {
            "id": "47f6c121-7c96-436a-a972-814bb0dd5f8c",
            "name": "Montverde Hotel 1",
            "address": "5171 Montverde St",
            "city": "Montverde",
            "state": "FL",
            "country_code": "US",
            "hotel_rating": 2.7,
            "phone_number": "+1 305 555 1735",
            "website": null
        },
        {
            "id": "46f4f611-1b74-4b25-9a2d-73a44bc4be15",
            "name": "Montverde Hotel 2",
            "address": "9133 Montverde St",
            "city": "Montverde",
            "state": "FL",
            "country_code": "US",
            "hotel_rating": 3.2,
            "phone_number": "+1 305 555 4523",
            "website": null
        },
        {
            "id": "20993e4b-f115-4db0-8623-6e91a6d56c8f",
            "name": "Montverde Hotel 3",
            "address": "6588 Montverde St",
            "city": "Montverde",
            "state": "FL",
            "country_code": "US",
            "hotel_rating": 4.1,
            "phone_number": "+1 305 555 8468",
            "website": null
        },
        {
            "id": "8b5e7f23-7b34-40dc-b27d-d2624219abbe",
            "name": "Montverde Hotel 4",
            "address": "7329 Montverde St",
            "city": "Montverde",
            "state": "FL",
            "country_code": "US",
            "hotel_rating": 3.4,
            "phone_number": "+1 305 555 3260",
            "website": null
        },
        {
            "id": "54635181-61c0-4f96-b95f-3f97bfa4a6b2",
            "name": "Montverde Hotel 5",
            "address": "5127 Montverde St",
            "city": "Montverde",
            "state": "FL",
            "country_code": "US",
            "hotel_rating": 4.4,
            "phone_number": "+1 305 555 7047",
            "website": null
        },
        {
            "id": "7f868484-066e-4e7c-bda2-151516732931",
            "name": "Montverde Hotel 6",
            "address": "626 Montverde St",
            "city": "Montverde",
            "state": "FL",
            "country_code": "US",
            "hotel_rating": 2.2,
            "phone_number": "+1 305 555 3925",
            "website": null
        },
        {
            "id": "1035b6f7-e58d-40b2-89b6-0fde6cc33240",
            "name": "New York Hotel 1",
            "address": "7938 New York St",
            "city": "New York",
            "state": "FL",
            "country_code": "US",
            "hotel_rating": 2.3,
            "phone_number": "+1 305 555 3438",
            "website": null
        },
        {
            "id": "2b51f445-a759-46c6-989f-9ba23035e9ca",
            "name": "New York Hotel 2",
            "address": "5013 New York St",
            "city": "New York",
            "state": "FL",
            "country_code": "US",
            "hotel_rating": 4.7,
            "phone_number": "+1 305 555 4955",
            "website": null
        },
        {
            "id": "04f83c13-207c-4566-824c-d58fafbc6bad",
            "name": "New York Hotel 3",
            "address": "9236 New York St",
            "city": "New York",
            "state": "FL",
            "country_code": "US",
            "hotel_rating": 3.9,
            "phone_number": "+1 305 555 9060",
            "website": null
        },
        {
            "id": "121d2a97-a460-435d-a698-e14ad5dd602e",
            "name": "New York Hotel 4",
            "address": "6987 New York St",
            "city": "New York",
            "state": "FL",
            "country_code": "US",
            "hotel_rating": 3.9,
            "phone_number": "+1 305 555 6619",
            "website": null
        },
        {
            "id": "a9514371-1497-47f1-bd03-4ec7757a0b81",
            "name": "New York Hotel 5",
            "address": "7683 New York St",
            "city": "New York",
            "state": "FL",
            "country_code": "US",
            "hotel_rating": 2.4,
            "phone_number": "+1 305 555 5749",
            "website": null
        },
        {
            "id": "2211d4cd-8804-4a5e-b6f7-7a09acf1a737",
            "name": "New York Hotel 6",
            "address": "2186 New York St",
            "city": "New York",
            "state": "FL",
            "country_code": "US",
            "hotel_rating": 3.2,
            "phone_number": "+1 305 555 5359",
            "website": null
        },
        {
            "id": "9c9bb6ec-043a-4797-b6fa-06f16648f564",
            "name": "Ocoee Hotel 1",
            "address": "9703 Ocoee St",
            "city": "Ocoee",
            "state": "FL",
            "country_code": "US",
            "hotel_rating": 2.6,
            "phone_number": "+1 305 555 6759",
            "website": null
        },
        {
            "id": "784a33b7-b244-4332-b633-c245ceec46ed",
            "name": "Ocoee Hotel 2",
            "address": "311 Ocoee St",
            "city": "Ocoee",
            "state": "FL",
            "country_code": "US",
            "hotel_rating": 4.5,
            "phone_number": "+1 305 555 8453",
            "website": null
        },
        {
            "id": "d6b86312-a101-4d71-abcb-f15e90227aa9",
            "name": "Ocoee Hotel 3",
            "address": "3123 Ocoee St",
            "city": "Ocoee",
            "state": "FL",
            "country_code": "US",
            "hotel_rating": 2.7,
            "phone_number": "+1 305 555 6262",
            "website": null
        },
        {
            "id": "96afd486-89ce-42bc-8312-ef2d88db0be6",
            "name": "Ocoee Hotel 4",
            "address": "5346 Ocoee St",
            "city": "Ocoee",
            "state": "FL",
            "country_code": "US",
            "hotel_rating": 3.3,
            "phone_number": "+1 305 555 4661",
            "website": null
        },
        {
            "id": "c1bb0bc2-2e88-457d-b6af-d3110e8ec0c8",
            "name": "Ocoee Hotel 5",
            "address": "7395 Ocoee St",
            "city": "Ocoee",
            "state": "FL",
            "country_code": "US",
            "hotel_rating": 3.4,
            "phone_number": "+1 305 555 2258",
            "website": null
        },
        {
            "id": "1dce15af-0759-429f-bd85-019686722430",
            "name": "Ocoee Hotel 6",
            "address": "2510 Ocoee St",
            "city": "Ocoee",
            "state": "FL",
            "country_code": "US",
            "hotel_rating": 3.4,
            "phone_number": "+1 305 555 7531",
            "website": null
        },
        {
            "id": "db888dc3-9da0-4e1c-816e-b12e97392aa7",
            "name": "Orlando area Hotel 1",
            "address": "9947 Orlando area St",
            "city": "Orlando area",
            "state": "FL",
            "country_code": "US",
            "hotel_rating": 4.2,
            "phone_number": "+1 305 555 9017",
            "website": null
        },
        {
            "id": "5d926127-64bb-4f03-9764-2368882fd5b0",
            "name": "Orlando area Hotel 2",
            "address": "8572 Orlando area St",
            "city": "Orlando area",
            "state": "FL",
            "country_code": "US",
            "hotel_rating": 4.8,
            "phone_number": "+1 305 555 9479",
            "website": null
        },
        {
            "id": "bd0ecceb-5d25-4cce-b1b6-21c18e9eacfe",
            "name": "Orlando area Hotel 3",
            "address": "6485 Orlando area St",
            "city": "Orlando area",
            "state": "FL",
            "country_code": "US",
            "hotel_rating": 2.5,
            "phone_number": "+1 305 555 6352",
            "website": null
        },
        {
            "id": "45eebced-1c76-46b3-ae82-eb9159b73921",
            "name": "Orlando area Hotel 4",
            "address": "4306 Orlando area St",
            "city": "Orlando area",
            "state": "FL",
            "country_code": "US",
            "hotel_rating": 4.6,
            "phone_number": "+1 305 555 9680",
            "website": null
        },
        {
            "id": "8ea1ef6c-ad8c-45e6-8476-15d65d97afd2",
            "name": "Orlando area Hotel 5",
            "address": "385 Orlando area St",
            "city": "Orlando area",
            "state": "FL",
            "country_code": "US",
            "hotel_rating": 3.3,
            "phone_number": "+1 305 555 8788",
            "website": null
        },
        {
            "id": "1d4ebae5-bd0a-476b-89cd-1669d38be805",
            "name": "Orlando area Hotel 6",
            "address": "3763 Orlando area St",
            "city": "Orlando area",
            "state": "FL",
            "country_code": "US",
            "hotel_rating": 4.5,
            "phone_number": "+1 305 555 5334",
            "website": null
        },
        {
            "id": "0efc006b-e052-4c08-befe-444a34003ca0",
            "name": "Poinciana Hotel 1",
            "address": "7848 Poinciana St",
            "city": "Poinciana",
            "state": "FL",
            "country_code": "US",
            "hotel_rating": 4.6,
            "phone_number": "+1 305 555 6231",
            "website": null
        },
        {
            "id": "eca077b8-faa1-4dca-abd0-9baa23e489aa",
            "name": "Poinciana Hotel 2",
            "address": "2070 Poinciana St",
            "city": "Poinciana",
            "state": "FL",
            "country_code": "US",
            "hotel_rating": 2.5,
            "phone_number": "+1 305 555 8392",
            "website": null
        },
        {
            "id": "fda339a3-46f4-4b4b-89f3-8e3ea2bd9a90",
            "name": "Poinciana Hotel 3",
            "address": "3357 Poinciana St",
            "city": "Poinciana",
            "state": "FL",
            "country_code": "US",
            "hotel_rating": 3.5,
            "phone_number": "+1 305 555 9862",
            "website": null
        },
        {
            "id": "c3b0aa48-897f-405b-8baf-7191d7040d89",
            "name": "Poinciana Hotel 4",
            "address": "7781 Poinciana St",
            "city": "Poinciana",
            "state": "FL",
            "country_code": "US",
            "hotel_rating": 4.7,
            "phone_number": "+1 305 555 3642",
            "website": null
        },
        {
            "id": "d7d9b7a3-625c-4976-9c32-e4bf3ab16deb",
            "name": "Poinciana Hotel 5",
            "address": "1734 Poinciana St",
            "city": "Poinciana",
            "state": "FL",
            "country_code": "US",
            "hotel_rating": 4.9,
            "phone_number": "+1 305 555 4895",
            "website": null
        },
        {
            "id": "767f7a2c-6506-4185-a156-4fff0d03cc78",
            "name": "Poinciana Hotel 6",
            "address": "4427 Poinciana St",
            "city": "Poinciana",
            "state": "FL",
            "country_code": "US",
            "hotel_rating": 3.7,
            "phone_number": "+1 305 555 5861",
            "website": null
        },
        {
            "id": "33c2aa88-7427-4658-8558-d5e1b0b9ad22",
            "name": "Polk City Hotel 1",
            "address": "5852 Polk City St",
            "city": "Polk City",
            "state": "FL",
            "country_code": "US",
            "hotel_rating": 4.7,
            "phone_number": "+1 305 555 1480",
            "website": null
        },
        {
            "id": "f876181a-2f8a-45e8-89c9-57edecc44594",
            "name": "Polk City Hotel 2",
            "address": "3986 Polk City St",
            "city": "Polk City",
            "state": "FL",
            "country_code": "US",
            "hotel_rating": 2.4,
            "phone_number": "+1 305 555 1289",
            "website": null
        },
        {
            "id": "27065104-45ab-472b-aa9e-2eefd21d9b81",
            "name": "Polk City Hotel 3",
            "address": "2733 Polk City St",
            "city": "Polk City",
            "state": "FL",
            "country_code": "US",
            "hotel_rating": 4.9,
            "phone_number": "+1 305 555 2496",
            "website": null
        },
        {
            "id": "eb714e64-3287-4596-805d-4f5506507016",
            "name": "Polk City Hotel 4",
            "address": "4474 Polk City St",
            "city": "Polk City",
            "state": "FL",
            "country_code": "US",
            "hotel_rating": 3.2,
            "phone_number": "+1 305 555 1375",
            "website": null
        },
        {
            "id": "9cad9723-afa7-4c76-a55a-8c7351e6b2e2",
            "name": "Polk City Hotel 5",
            "address": "2980 Polk City St",
            "city": "Polk City",
            "state": "FL",
            "country_code": "US",
            "hotel_rating": 2.9,
            "phone_number": "+1 305 555 3781",
            "website": null
        },
        {
            "id": "d20cf0b2-7855-49e3-b423-09525026cfcb",
            "name": "Polk City Hotel 6",
            "address": "426 Polk City St",
            "city": "Polk City",
            "state": "FL",
            "country_code": "US",
            "hotel_rating": 4.4,
            "phone_number": "+1 305 555 1856",
            "website": null
        },
        {
            "id": "4841454f-4513-432f-bfa6-eb799577405a",
            "name": "San Francisco Bay Hotel 1",
            "address": "2100 San Francisco Bay St",
            "city": "San Francisco Bay",
            "state": "FL",
            "country_code": "US",
            "hotel_rating": 2.8,
            "phone_number": "+1 305 555 8431",
            "website": null
        },
        {
            "id": "4203cf25-5b07-4a03-a1e5-b73e72258149",
            "name": "San Francisco Bay Hotel 2",
            "address": "3886 San Francisco Bay St",
            "city": "San Francisco Bay",
            "state": "FL",
            "country_code": "US",
            "hotel_rating": 4.3,
            "phone_number": "+1 305 555 9452",
            "website": null
        },
        {
            "id": "abe3d745-395a-4ee6-b0df-7a44a8337b03",
            "name": "San Francisco Bay Hotel 3",
            "address": "2734 San Francisco Bay St",
            "city": "San Francisco Bay",
            "state": "FL",
            "country_code": "US",
            "hotel_rating": 4.4,
            "phone_number": "+1 305 555 6961",
            "website": null
        },
        {
            "id": "0c60d661-37f5-4cc9-a341-1a62d8346237",
            "name": "San Francisco Bay Hotel 4",
            "address": "3017 San Francisco Bay St",
            "city": "San Francisco Bay",
            "state": "FL",
            "country_code": "US",
            "hotel_rating": 2.4,
            "phone_number": "+1 305 555 2762",
            "website": null
        },
        {
            "id": "9fdf5cdb-5bce-4512-8a5c-7a97b419207d",
            "name": "San Francisco Bay Hotel 5",
            "address": "7768 San Francisco Bay St",
            "city": "San Francisco Bay",
            "state": "FL",
            "country_code": "US",
            "hotel_rating": 4.1,
            "phone_number": "+1 305 555 7580",
            "website": null
        },
        {
            "id": "2f732517-7349-4d7c-b0d8-5d996a81e31b",
            "name": "San Francisco Bay Hotel 6",
            "address": "5299 San Francisco Bay St",
            "city": "San Francisco Bay",
            "state": "FL",
            "country_code": "US",
            "hotel_rating": 2.5,
            "phone_number": "+1 305 555 9575",
            "website": null
        },
        {
            "id": "bd9e9752-514e-42d2-929b-fd473271f221",
            "name": "St. Cloud Hotel 1",
            "address": "685 St. Cloud St",
            "city": "St. Cloud",
            "state": "FL",
            "country_code": "US",
            "hotel_rating": 2.7,
            "phone_number": "+1 305 555 9867",
            "website": null
        },
        {
            "id": "a24b69a6-59f0-43ed-ba49-da4722e7feaf",
            "name": "St. Cloud Hotel 2",
            "address": "4127 St. Cloud St",
            "city": "St. Cloud",
            "state": "FL",
            "country_code": "US",
            "hotel_rating": 2.5,
            "phone_number": "+1 305 555 9421",
            "website": null
        },
        {
            "id": "da99350c-639c-4086-b2c6-2caa8da3ddc1",
            "name": "St. Cloud Hotel 3",
            "address": "904 St. Cloud St",
            "city": "St. Cloud",
            "state": "FL",
            "country_code": "US",
            "hotel_rating": 2.6,
            "phone_number": "+1 305 555 2610",
            "website": null
        },
        {
            "id": "21159fc1-ca3d-4ee7-b0ab-f0cf13d72383",
            "name": "St. Cloud Hotel 4",
            "address": "459 St. Cloud St",
            "city": "St. Cloud",
            "state": "FL",
            "country_code": "US",
            "hotel_rating": 3.3,
            "phone_number": "+1 305 555 5141",
            "website": null
        },
        {
            "id": "65e55439-96ce-4ed4-9416-737a64d921e5",
            "name": "St. Cloud Hotel 5",
            "address": "8883 St. Cloud St",
            "city": "St. Cloud",
            "state": "FL",
            "country_code": "US",
            "hotel_rating": 2.4,
            "phone_number": "+1 305 555 3360",
            "website": null
        },
        {
            "id": "a41cc918-0ed6-4f52-abdd-685a503b31a2",
            "name": "St. Cloud Hotel 6",
            "address": "1169 St. Cloud St",
            "city": "St. Cloud",
            "state": "FL",
            "country_code": "US",
            "hotel_rating": 4.2,
            "phone_number": "+1 305 555 7346",
            "website": null
        },
        {
            "id": "7620ada2-c8c5-4192-b32a-60d790b56c46",
            "name": "Walt Disney World\u00ae Resort Hotel 1",
            "address": "4550 Walt Disney World\u00ae Resort St",
            "city": "Walt Disney World\u00ae Resort",
            "state": "FL",
            "country_code": "US",
            "hotel_rating": 4.0,
            "phone_number": "+1 305 555 8410",
            "website": null
        },
        {
            "id": "397cf3ae-8445-4788-8ab7-5b81a2a90f19",
            "name": "Walt Disney World\u00ae Resort Hotel 2",
            "address": "6230 Walt Disney World\u00ae Resort St",
            "city": "Walt Disney World\u00ae Resort",
            "state": "FL",
            "country_code": "US",
            "hotel_rating": 2.8,
            "phone_number": "+1 305 555 2850",
            "website": null
        },
        {
            "id": "57af21d7-1af0-4aa8-8f87-b8a6f7a0514c",
            "name": "Walt Disney World\u00ae Resort Hotel 3",
            "address": "2540 Walt Disney World\u00ae Resort St",
            "city": "Walt Disney World\u00ae Resort",
            "state": "FL",
            "country_code": "US",
            "hotel_rating": 3.2,
            "phone_number": "+1 305 555 1508",
            "website": null
        },
        {
            "id": "58c01a3c-7c3b-4d67-9917-3d357a192a18",
            "name": "Walt Disney World\u00ae Resort Hotel 4",
            "address": "5597 Walt Disney World\u00ae Resort St",
            "city": "Walt Disney World\u00ae Resort",
            "state": "FL",
            "country_code": "US",
            "hotel_rating": 4.8,
            "phone_number": "+1 305 555 7849",
            "website": null
        },
        {
            "id": "f279a75e-4622-4049-8fc3-7c260838687b",
            "name": "Walt Disney World\u00ae Resort Hotel 5",
            "address": "6811 Walt Disney World\u00ae Resort St",
            "city": "Walt Disney World\u00ae Resort",
            "state": "FL",
            "country_code": "US",
            "hotel_rating": 4.3,
            "phone_number": "+1 305 555 3073",
            "website": null
        },
        {
            "id": "858c29bb-151d-4c32-bd2e-32b6704b782f",
            "name": "Walt Disney World\u00ae Resort Hotel 6",
            "address": "8781 Walt Disney World\u00ae Resort St",
            "city": "Walt Disney World\u00ae Resort",
            "state": "FL",
            "country_code": "US",
            "hotel_rating": 2.3,
            "phone_number": "+1 305 555 6871",
            "website": null
        },
        {
            "id": "17bc1a46-c3d2-4c39-9b53-189282228cb3",
            "name": "Washington Hotel 1",
            "address": "5040 Washington St",
            "city": "Washington",
            "state": "FL",
            "country_code": "US",
            "hotel_rating": 2.5,
            "phone_number": "+1 305 555 1519",
            "website": null
        },
        {
            "id": "d9f95861-df47-4b4d-9ded-0ee613cd145c",
            "name": "Washington Hotel 2",
            "address": "4645 Washington St",
            "city": "Washington",
            "state": "FL",
            "country_code": "US",
            "hotel_rating": 3.7,
            "phone_number": "+1 305 555 8236",
            "website": null
        },
        {
            "id": "fce733d4-9c0d-43f5-8f72-0c893b1642f1",
            "name": "Washington Hotel 3",
            "address": "8211 Washington St",
            "city": "Washington",
            "state": "FL",
            "country_code": "US",
            "hotel_rating": 2.0,
            "phone_number": "+1 305 555 8678",
            "website": null
        },
        {
            "id": "f35bda61-8649-455d-b26f-9ce8c0e93691",
            "name": "Washington Hotel 4",
            "address": "8058 Washington St",
            "city": "Washington",
            "state": "FL",
            "country_code": "US",
            "hotel_rating": 4.9,
            "phone_number": "+1 305 555 3508",
            "website": null
        },
        {
            "id": "3b31dbb3-e0fc-41ac-875e-c34010f553fb",
            "name": "Washington Hotel 5",
            "address": "6913 Washington St",
            "city": "Washington",
            "state": "FL",
            "country_code": "US",
            "hotel_rating": 2.7,
            "phone_number": "+1 305 555 2634",
            "website": null
        },
        {
            "id": "f6aa9111-b04c-4ed5-aaf0-b1abf2b979bc",
            "name": "Washington Hotel 6",
            "address": "7491 Washington St",
            "city": "Washington",
            "state": "FL",
            "country_code": "US",
            "hotel_rating": 4.5,
            "phone_number": "+1 305 555 5475",
            "website": null
        },
        {
            "id": "d65b3a1d-1713-4cd5-915a-142dffad19ac",
            "name": "Windermere Hotel 1",
            "address": "135 Windermere St",
            "city": "Windermere",
            "state": "FL",
            "country_code": "US",
            "hotel_rating": 3.2,
            "phone_number": "+1 305 555 4150",
            "website": null
        },
        {
            "id": "d25db8cf-9a0d-4618-bb4a-890bcdeb2a7a",
            "name": "Windermere Hotel 2",
            "address": "8047 Windermere St",
            "city": "Windermere",
            "state": "FL",
            "country_code": "US",
            "hotel_rating": 4.4,
            "phone_number": "+1 305 555 1084",
            "website": null
        },
        {
            "id": "8083c3b5-e880-4888-873f-2da40cd4ce63",
            "name": "Windermere Hotel 3",
            "address": "6269 Windermere St",
            "city": "Windermere",
            "state": "FL",
            "country_code": "US",
            "hotel_rating": 2.8,
            "phone_number": "+1 305 555 9385",
            "website": null
        },
        {
            "id": "8305418f-2ae8-45ac-941c-137c4267d51c",
            "name": "Windermere Hotel 4",
            "address": "8833 Windermere St",
            "city": "Windermere",
            "state": "FL",
            "country_code": "US",
            "hotel_rating": 4.4,
            "phone_number": "+1 305 555 9412",
            "website": null
        },
        {
            "id": "cb350045-3cbe-49f1-bb2a-cbcc09a204de",
            "name": "Windermere Hotel 5",
            "address": "4643 Windermere St",
            "city": "Windermere",
            "state": "FL",
            "country_code": "US",
            "hotel_rating": 3.4,
            "phone_number": "+1 305 555 2752",
            "website": null
        },
        {
            "id": "7fc0af94-80fe-4a63-99cf-39bbcecf5001",
            "name": "Windermere Hotel 6",
            "address": "7503 Windermere St",
            "city": "Windermere",
            "state": "FL",
            "country_code": "US",
            "hotel_rating": 4.5,
            "phone_number": "+1 305 555 9406",
            "website": null
        },
        {
            "id": "49d5dc0c-c40e-422d-ae9e-5e557bc558bd",
            "name": "Winter Garden Hotel 1",
            "address": "9972 Winter Garden St",
            "city": "Winter Garden",
            "state": "FL",
            "country_code": "US",
            "hotel_rating": 4.4,
            "phone_number": "+1 305 555 7909",
            "website": null
        },
        {
            "id": "9e4c397f-ac33-4a92-82d7-9b07af71fa20",
            "name": "Winter Garden Hotel 2",
            "address": "5013 Winter Garden St",
            "city": "Winter Garden",
            "state": "FL",
            "country_code": "US",
            "hotel_rating": 4.3,
            "phone_number": "+1 305 555 9920",
            "website": null
        },
        {
            "id": "8e8b342b-0121-4770-943b-4ec6bb1c304b",
            "name": "Winter Garden Hotel 3",
            "address": "1376 Winter Garden St",
            "city": "Winter Garden",
            "state": "FL",
            "country_code": "US",
            "hotel_rating": 2.4,
            "phone_number": "+1 305 555 9337",
            "website": null
        },
        {
            "id": "5ddf1431-f509-4ad5-9fa8-435220f03a87",
            "name": "Winter Garden Hotel 4",
            "address": "3383 Winter Garden St",
            "city": "Winter Garden",
            "state": "FL",
            "country_code": "US",
            "hotel_rating": 3.4,
            "phone_number": "+1 305 555 2279",
            "website": null
        },
        {
            "id": "4db73126-a90d-4923-913b-11a513292dc0",
            "name": "Winter Garden Hotel 5",
            "address": "1616 Winter Garden St",
            "city": "Winter Garden",
            "state": "FL",
            "country_code": "US",
            "hotel_rating": 3.9,
            "phone_number": "+1 305 555 1596",
            "website": null
        },
        {
            "id": "24a3b6a3-f3b3-41e6-98ec-d0948739853b",
            "name": "Winter Garden Hotel 6",
            "address": "2169 Winter Garden St",
            "city": "Winter Garden",
            "state": "FL",
            "country_code": "US",
            "hotel_rating": 2.7,
            "phone_number": "+1 305 555 9803",
            "website": null
        }
    ]
}
